{
    "modelId": "dtmi:com:contoso:digital_factory:cheese_factory:cheese_cave_device;2",
    "patch": [
        {
            "value": false,
            "path": "/fanAlert",
            "op": "replace"
        },
        {
            "value": true,
            "path": "/temperatureAlert",
            "op": "replace"
        },
        {
            "value": true,
            "path": "/humidityAlert",
            "op": "replace"
        },
        {
            "value": 69.88,
            "path": "/temperature",
            "op": "replace"
        },
        {
            "value": 97.82,
            "path": "/humidity",
            "op": "replace"
        }
    ]
}